ramjam/__init__.py
ramjam/cli.py
ramjam/utils.py
ramjam-0.5.0.dist-info/LICENSE
ramjam-0.5.0.dist-info/METADATA
ramjam-0.5.0.dist-info/WHEEL
ramjam-0.5.0.dist-info/top_level.txt
ramjam-0.5.0.dist-info/RECORD
