Metadata-Version: 2.1
Name: ramjam
Version: 0.5.0
Requires-Python: >=3.9
License-File: LICENSE
Provides-Extra: dev
Requires-Dist: setuptools==67.6.0; extra == "dev"
Requires-Dist: build==0.10.0; extra == "dev"
Requires-Dist: python-semantic-release==7.33.2; extra == "dev"
Requires-Dist: pytest==7.2.2; extra == "dev"
Requires-Dist: black==22.6.0; extra == "dev"
Requires-Dist: isort==5.12.0; extra == "dev"
Provides-Extra: docs
Requires-Dist: mkdocs==1.4.2; extra == "docs"
Requires-Dist: mkdocstrings[python]==0.20.0; extra == "docs"
Requires-Dist: mkdocs-material==9.1.3; extra == "docs"
